svr_tts/__init__.py
svr_tts/core.py
svr_tts/utils.py
svr_tts-0.11.3.dist-info/METADATA
svr_tts-0.11.3.dist-info/WHEEL
svr_tts-0.11.3.dist-info/top_level.txt
svr_tts-0.11.3.dist-info/RECORD
