Metadata-Version: 2.4
Name: svr_tts
Version: 0.11.3
Summary: Синтез речи
Author: Selector
Requires-Dist: onnxruntime-gpu
Requires-Dist: numpy
Requires-Dist: huggingface_hub
Requires-Dist: appdirs
Requires-Dist: tqdm
Requires-Dist: requests
Requires-Dist: resampy
Dynamic: author
Dynamic: requires-dist
Dynamic: summary
